redis_lock/__init__.py
redis_lock/django_cache.py
python_redis_lock-4.0.0.dist-info/AUTHORS.rst
python_redis_lock-4.0.0.dist-info/LICENSE
python_redis_lock-4.0.0.dist-info/METADATA
python_redis_lock-4.0.0.dist-info/WHEEL
python_redis_lock-4.0.0.dist-info/top_level.txt
python_redis_lock-4.0.0.dist-info/RECORD
